scoring/__init__.py
scoring/bivariate.py
scoring/cleanning.py
scoring/discretization.py
scoring/evaluation.py
scoring/scoring.py
scoring-0.0.9.dist-info/LICENSE
scoring-0.0.9.dist-info/METADATA
scoring-0.0.9.dist-info/WHEEL
scoring-0.0.9.dist-info/top_level.txt
scoring-0.0.9.dist-info/RECORD
